{
  "version": "1.0",
  "domain": "berunactivewear.com",
  "auto_register": false,
  "tags": [
    {
      "slug": "oem",
      "name": "OEM",
      "description": "OEM manufacturing articles — custom activewear produced to a buyer's own brand and spec.",
      "aliases": [
        "oem manufacturing",
        "oem activewear",
        "oem sportswear",
        "cut and sew oem"
      ]
    },
    {
      "slug": "odm",
      "name": "ODM",
      "description": "ODM design-plus-manufacturing articles — factory-developed styles buyers can white-label.",
      "aliases": [
        "odm manufacturing",
        "odm sportswear",
        "design plus manufacturing"
      ]
    },
    {
      "slug": "private-label",
      "name": "Private Label",
      "description": "Private-label activewear articles — your brand label on factory-run production.",
      "aliases": [
        "private label activewear",
        "white label activewear",
        "private labelling"
      ]
    },
    {
      "slug": "low-moq",
      "name": "Low MOQ",
      "description": "Low-MOQ and small-batch sourcing articles for emerging activewear brands.",
      "aliases": [
        "low moq",
        "small batch",
        "small minimum order",
        "low minimum order quantity"
      ]
    },
    {
      "slug": "sampling",
      "name": "Sampling",
      "description": "Sampling and pre-production articles — sample cost, lead time, fit approval.",
      "aliases": [
        "sample",
        "pre-production sample",
        "sampling service",
        "fit sample"
      ]
    },
    {
      "slug": "tech-pack",
      "name": "Tech-Pack",
      "description": "Tech-pack, pattern and grading articles — what to send before sampling.",
      "aliases": [
        "tech pack",
        "techpack",
        "spec sheet",
        "pattern making",
        "grading"
      ]
    },
    {
      "slug": "moisture-wicking",
      "name": "Moisture-Wicking",
      "description": "Moisture-wicking and quick-dry performance fabric articles.",
      "aliases": [
        "moisture wicking",
        "sweat wicking",
        "quick dry",
        "wicking fabric"
      ]
    },
    {
      "slug": "four-way-stretch",
      "name": "Four-Way Stretch",
      "description": "Four-way stretch fabric and construction articles for activewear fit and recovery.",
      "aliases": [
        "four way stretch",
        "4-way stretch",
        "stretch fabric",
        "spandex blend"
      ]
    },
    {
      "slug": "recycled-fabric",
      "name": "Recycled Fabric",
      "description": "Recycled and sustainable fabric articles — rPET, GRS, eco-friendly activewear.",
      "aliases": [
        "recycled polyester",
        "rpet",
        "sustainable fabric",
        "grs",
        "eco fabric"
      ]
    },
    {
      "slug": "sublimation",
      "name": "Sublimation",
      "description": "Sublimation and all-over print articles — dye-sublimation decoration for sportswear.",
      "aliases": [
        "sublimation printing",
        "dye sublimation",
        "all-over print",
        "all over print"
      ]
    },
    {
      "slug": "private-label-brand",
      "name": "Private Label Brand",
      "description": "Insights and tips on starting and growing your own private label activewear brand in a competitive market.",
      "aliases": [
        "private label activewear brand",
        "private label brand",
        "private label clothing brand",
        "activewear private label",
        "custom activewear brand"
      ]
    },
    {
      "slug": "activewear-oem",
      "name": "Activewear OEM",
      "description": "Expert guidance and insights on private label activewear manufacturing for launching your brand successfully in 2026 and beyond.",
      "aliases": [
        "private label activewear manufacturer",
        "activewear oem",
        "private label activewear",
        "activewear manufacturer",
        "custom activewear manufacturer"
      ]
    },
    {
      "slug": "low-moq-2",
      "name": "Low MOQ",
      "description": "Low MOQ manufacturing options for activewear brands help startups produce smaller runs affordably with high quality standards.",
      "aliases": [
        "low moq activewear manufacturer",
        "low moq manufacturer",
        "small batch activewear",
        "low minimum order quantity",
        "low moq apparel"
      ]
    },
    {
      "slug": "start-brand",
      "name": "Start Brand",
      "description": "Guides and tips on starting your own private label activewear brand successfully in 2026 and beyond.",
      "aliases": [
        "start activewear brand 2026",
        "launch activewear brand",
        "begin activewear brand",
        "start private label brand",
        "how to start activewear brand"
      ]
    },
    {
      "slug": "brand-launch",
      "name": "Brand Launch",
      "description": "Comprehensive guides and tips on launching your activewear brand successfully in the competitive market.",
      "aliases": [
        "activewear brand launch guide",
        "activewear brand launch",
        "start activewear brand",
        "launch activewear brand",
        "activewear brand startup",
        "activewear brand tips"
      ]
    },
    {
      "slug": "sports-bra-style",
      "name": "Sports Bra Style",
      "description": "Explore trendy sports bra outfit ideas and styling tips for creating fashionable and comfortable summer looks.",
      "aliases": [
        "sports bra outfit ideas",
        "sports bra outfits",
        "sports bra styling",
        "sport bra looks",
        "athleisure bra outfits"
      ]
    },
    {
      "slug": "summer-looks",
      "name": "Summer Looks",
      "description": "Trendy and stylish summer outfit ideas inspired by sports bras for fashionable women in 2026 and beyond.",
      "aliases": [
        "sports bra summer looks 2026",
        "summer sports bra outfits",
        "2026 summer sports bra styles",
        "summer looks 2026",
        "sports bra summer fashion",
        "summer sportswear 2026"
      ]
    },
    {
      "slug": "athleisure",
      "name": "Athleisure",
      "description": "Athleisure style blends athletic and casual wear for versatile, comfortable summer outfits that combine fashion and function effortlessly.",
      "aliases": [
        "athleisure summer style",
        "athleisure wear",
        "summer athleisure",
        "athleisure fashion",
        "athleisure outfits",
        "athleisure clothing"
      ]
    },
    {
      "slug": "sports-bra-pants",
      "name": "Sports Bra + Pants",
      "description": "Articles and styling tips featuring sports bras paired with high waisted pants for trendy and comfortable summer looks in activewear.",
      "aliases": [
        "sports bra with high waisted pants",
        "sports bra high waist pants",
        "sports bra paired with pants",
        "high waisted pants and sports bra",
        "athleisure sports bra pants",
        "sports bra with pants outfit"
      ]
    },
    {
      "slug": "sports-bra-cardigan",
      "name": "Bra & Cardigan",
      "description": "Style tips and outfits combining sports bras with cardigans for a trendy layered look in summer and transitional seasons.",
      "aliases": [
        "sports bra with cardigan",
        "bra and cardigan",
        "sports bra cardigan outfit",
        "cardigan over sports bra",
        "layered sports bra look"
      ]
    },
    {
      "slug": "custom-bra",
      "name": "Custom Bra",
      "description": "Insights and trends on custom sports bra design for tailored fit, style, and performance in activewear collections.",
      "aliases": [
        "custom sports bra design",
        "custom bra design",
        "custom sports bra",
        "bespoke sports bra",
        "personalized sports bra"
      ]
    },
    {
      "slug": "private-labelling",
      "name": "Private Labelling",
      "description": "Articles focused on private labelling strategies and benefits specifically tailored for fitness centres and wellness brands.",
      "aliases": [
        "private labelling fitness centre",
        "private labeling fitness center",
        "fitness centre private labelling",
        "custom labelling fitness centre",
        "private label fitness centre",
        "private labelling gym apparel"
      ]
    },
    {
      "slug": "gym-private-label",
      "name": "Gym Private Label",
      "description": "Articles covering private labeling options tailored specifically for gym and fitness center products and apparel.",
      "aliases": [
        "gym private label products",
        "fitness center private label",
        "private labeling gym apparel",
        "gym custom products",
        "private label fitness gear"
      ]
    },
    {
      "slug": "brand-identity",
      "name": "Brand Identity",
      "description": "Insights and strategies on creating a strong fitness brand identity to enhance recognition and customer loyalty in activewear markets.",
      "aliases": [
        "fitness brand identity",
        "brand identity fitness",
        "fitness branding",
        "brand image fitness",
        "fitness brand strategy"
      ]
    },
    {
      "slug": "custom-gym",
      "name": "Custom Gym",
      "description": "Custom branded gym merchandise and apparel for fitness centers to boost brand visibility and client engagement effectively.",
      "aliases": [
        "custom branded gym merchandise",
        "custom gym merchandise",
        "branded gym apparel",
        "gym custom branding",
        "fitness center custom merch"
      ]
    },
    {
      "slug": "private-gym",
      "name": "Private Gym",
      "description": "Private label activewear designed specifically for gyms and fitness centers to enhance brand identity and customer loyalty.",
      "aliases": [
        "private label activewear gym",
        "gym private label",
        "private label gym wear",
        "custom gym activewear",
        "private gym apparel"
      ]
    },
    {
      "slug": "swimwear-trends",
      "name": "Swimwear Trends",
      "description": "Latest insights and updates on swimwear wholesale trends and styles to watch out for in 2026 and beyond.",
      "aliases": [
        "swimwear wholesale trends 2026",
        "2026 swimwear trends",
        "swimwear trends 2026",
        "wholesale swimwear trends",
        "swimwear fashion 2026"
      ]
    },
    {
      "slug": "swimwear",
      "name": "Swimwear",
      "description": "Insights and trends on swimwear wholesale, including one-piece styles and market demands for upcoming seasons.",
      "aliases": [
        "one-piece swimsuit wholesale",
        "swimwear wholesale",
        "wholesale swimsuits",
        "one-piece swimwear",
        "wholesale one-piece swimsuit",
        "swimming costume wholesale"
      ]
    },
    {
      "slug": "private-swimwear",
      "name": "Private Swimwear",
      "description": "Insights and best practices for private label swimwear production, design, and branding in the swimwear wholesale market.",
      "aliases": [
        "private label swimwear",
        "private-label swimwear",
        "custom swimwear",
        "swimwear private label",
        "private swimwear branding",
        "swimwear custom label"
      ]
    },
    {
      "slug": "custom-swimwear",
      "name": "Custom Swimwear",
      "description": "Custom swimwear manufacturing focuses on tailored production and unique designs for swimwear brands and private labels.",
      "aliases": [
        "custom swimwear manufacturing",
        "swimwear manufacturing",
        "custom swimwear production",
        "private label swimwear",
        "swimwear oem",
        "custom swimwear maker"
      ]
    },
    {
      "slug": "sustainable-swim",
      "name": "Sustainable Swim",
      "description": "Sustainable swimwear wholesale trends, eco-friendly materials, and ethical production insights for the swimwear industry in 2026.",
      "aliases": [
        "sustainable swimwear wholesale",
        "eco swimwear wholesale",
        "wholesale sustainable swimwear",
        "ethical swimwear wholesale",
        "green swimwear wholesale"
      ]
    },
    {
      "slug": "plus-size-swim",
      "name": "Plus Size Swim",
      "description": "Insights and sourcing tips for plus size swimwear wholesale, focusing on trends, fit, and market demand in swimwear collections.",
      "aliases": [
        "plus size swimwear wholesale",
        "plus size swimsuits wholesale",
        "plus size swim bulk",
        "wholesale plus size swim",
        "plus size swimwear bulk",
        "plus size bathing suits wholesale",
        "plus-size swimwear wholesale"
      ]
    },
    {
      "slug": "upf-resort",
      "name": "UPF Resort",
      "description": "UPF resort wear wholesale focusing on sun-protective, stylish clothing perfect for resort and beach environments.",
      "aliases": [
        "upf resort wear wholesale",
        "resort upf clothing",
        "wholesale upf resort wear",
        "upf resort apparel",
        "sun protective resort wear"
      ]
    },
    {
      "slug": "nigeria-oem",
      "name": "Nigeria OEM",
      "description": "Leading sportswear manufacturers based in Nigeria specializing in OEM production for activewear and custom fitness apparel.",
      "aliases": [
        "sportswear manufacturers in nigeria",
        "nigeria sportswear oem",
        "nigerian activewear manufacturers",
        "sports apparel manufacturers nigeria",
        "nigeria fitness wear oem"
      ]
    },
    {
      "slug": "jersey-nigeria",
      "name": "Jersey Nigeria",
      "description": "Information and insights about jersey manufacturing companies and sportswear production in Nigeria, including top manufacturers and industry trends.",
      "aliases": [
        "jersey manufacturing companies nigeria",
        "nigeria jersey manufacturers",
        "jersey makers nigeria",
        "sportswear manufacturers nigeria",
        "jersey production nigeria"
      ]
    },
    {
      "slug": "nigeria-oem-2026",
      "name": "Nigeria OEM 2026",
      "description": "Insights and comprehensive guide on activewear manufacturers and OEM brands in Nigeria for the year 2026.",
      "aliases": [
        "activewear manufacturers nigeria 2026",
        "nigeria activewear oem 2026",
        "sportswear manufacturers nigeria 2026",
        "nigeria oem 2026",
        "nigeria sportswear oem 2026",
        "activewear nigeria 2026"
      ]
    },
    {
      "slug": "bulk-supplier-ng",
      "name": "Bulk Supplier NG",
      "description": "Reliable bulk sportswear supplier in Nigeria offering quality products and competitive pricing for manufacturers and retailers.",
      "aliases": [
        "bulk sportswear supplier nigeria",
        "bulk sportswear nigeria",
        "sportswear bulk supplier ng",
        "nigeria bulk sportswear",
        "bulk sports clothing supplier nigeria"
      ]
    },
    {
      "slug": "private-sportswear",
      "name": "Private Sportswear",
      "description": "Insights on private label sportswear manufacturing in Nigeria, detailing custom production and branding for local sports brands.",
      "aliases": [
        "private label sportswear nigeria",
        "private sportswear nigeria",
        "sportswear private label",
        "nigeria sportswear oem",
        "private label athletic wear",
        "custom sportswear nigeria"
      ]
    },
    {
      "slug": "retail-sales",
      "name": "Retail Sales",
      "description": "Strategies and tactics for activewear retailers to boost sales and grow their business in 2026 and beyond.",
      "aliases": [
        "activewear retailer sales tactics 2026",
        "activewear retail sales",
        "activewear sales strategies",
        "retail sales 2026",
        "activewear sales tips",
        "activewear retail growth"
      ]
    },
    {
      "slug": "athleisure-growth",
      "name": "Athleisure Growth",
      "description": "Insights and trends on the growth and expansion of the athleisure market through 2026, focusing on retail and consumer demand.",
      "aliases": [
        "athleisure market growth 2026",
        "athleisure growth",
        "athleisure market expansion",
        "activewear market growth",
        "athleisure sales growth",
        "athleisure market trends"
      ]
    },
    {
      "slug": "sales-growth",
      "name": "Sales Growth",
      "description": "Strategies and tips for activewear retailers to boost revenue and increase sales effectively in competitive markets.",
      "aliases": [
        "increase activewear sales",
        "activewear sales growth",
        "boost activewear sales",
        "grow activewear revenue",
        "activewear sales increase"
      ]
    },
    {
      "slug": "sales-tactics",
      "name": "Sales Tactics",
      "description": "Effective strategies and tactics for boosting athletic apparel sales in activewear retail markets in 2026 and beyond.",
      "aliases": [
        "athletic apparel sales tactics",
        "activewear sales strategies",
        "apparel sales tactics",
        "sportswear sales tips",
        "activewear retail sales",
        "athletic clothing sales"
      ]
    },
    {
      "slug": "dtc-strategy",
      "name": "DTC Strategy",
      "description": "Direct-to-consumer activewear strategy insights for brands aiming to boost retail sales and market reach in competitive landscapes.",
      "aliases": [
        "dtc activewear strategy",
        "direct to consumer activewear",
        "dtc sales strategy",
        "activewear dtc",
        "dtc retail strategy"
      ]
    },
    {
      "slug": "loyalty-program",
      "name": "Loyalty Program",
      "description": "Insights and strategies on activewear loyalty programs designed to enhance customer retention and boost sales for retailers.",
      "aliases": [
        "activewear loyalty program",
        "loyalty program for activewear",
        "activewear rewards program",
        "customer loyalty activewear",
        "activewear customer rewards"
      ]
    },
    {
      "slug": "micro-niche",
      "name": "Micro-Niche",
      "description": "Micro-niche activewear brands focus on specialized customer segments to boost sales and brand loyalty through targeted products and marketing.",
      "aliases": [
        "micro niche activewear brand",
        "micro-niche activewear",
        "micro niche fitness apparel",
        "targeted activewear brand",
        "niche activewear label",
        "micro-niche activewear brand"
      ]
    }
  ]
}
